zero_settings/__init__.py
zero_settings/settings.py
django_zero_settings-0.1.13.dist-info/LICENSE
django_zero_settings-0.1.13.dist-info/METADATA
django_zero_settings-0.1.13.dist-info/WHEEL
django_zero_settings-0.1.13.dist-info/top_level.txt
django_zero_settings-0.1.13.dist-info/RECORD
